msu_helpers/__init__.py
msu_helpers/database/__init__.py
msu_helpers/database/base.py
msu_helpers/database/db_constants.py
msu_helpers/database/extended.py
msu_helpers/database/managers.py
msu_helpers/database/models.py
msu_helpers/database/serializers.py
msu_helpers/http/__init__.py
msu_helpers/http/decorators.py
msu_helpers/http/http_constants.py
msu_helpers/http/responses/__init__.py
msu_helpers/http/responses/common_response.py
msu_helpers/interface/__init__.py
msu_helpers/interface/models/__init__.py
msu_helpers/interface/models/body/__init__.py
msu_helpers/interface/models/body/base.py
msu_helpers/interface/models/query/__init__.py
msu_helpers/interface/models/query/base.py
msu_helpers/interface/models/query/user.py
msu_helpers/middleware/__init__.py
msu_helpers/middleware/auth.py
msu_helpers/middleware/common.py
msu_helpers_dev-0.4.65.dist-info/METADATA
msu_helpers_dev-0.4.65.dist-info/WHEEL
msu_helpers_dev-0.4.65.dist-info/top_level.txt
msu_helpers_dev-0.4.65.dist-info/RECORD
